acutils/__init__.py
acutils/file.py
acutils/gpu.py
acutils/handler.py
acutils/image.py
acutils/multiprocess.py
acutils/pathology.py
acutils/sheet.py
acutils/video.py
acutils_python-0.1.1.dist-info/LICENSE
acutils_python-0.1.1.dist-info/METADATA
acutils_python-0.1.1.dist-info/WHEEL
acutils_python-0.1.1.dist-info/top_level.txt
acutils_python-0.1.1.dist-info/RECORD
