Metadata-Version: 2.1
Name: acutils-python
Version: 0.1.1
Summary: Data processing library implemented by Acuzle.
Author-email: Acuzle <contact@acuzle.com>, ThomasPDM <thomaspdm@acuzle.com>
Maintainer-email: Acuzle <contact@acuzle.com>, ThomasPDM <thomaspdm@acuzle.com>
License: Apache 2
Project-URL: repository, https://github.com/Acuzle/acutils
Project-URL: Homepage, https://github.com/Acuzle/acutils
Project-URL: Bug Tracker, https://github.com/Acuzle/acutils/issues
Classifier: Programming Language :: Python :: 3
Classifier: License :: OSI Approved :: Apache Software License
Classifier: Operating System :: OS Independent
Requires-Python: >=3.8
License-File: LICENSE
Requires-Dist: numpy
Requires-Dist: joblib
Requires-Dist: pandas
Requires-Dist: openpyxl
Requires-Dist: xlrd >=1.0.0
Provides-Extra: dependencies
Requires-Dist: scikit-image ; extra == 'dependencies'
Requires-Dist: opencv-python ; extra == 'dependencies'
Requires-Dist: Pillow ; extra == 'dependencies'
Requires-Dist: openslide-python ; extra == 'dependencies'
Requires-Dist: cupy ; extra == 'dependencies'
Requires-Dist: cucim ; extra == 'dependencies'
